_cffi__x11d28b3fx52abb3c3
nflog_cffi
scapy_nflog
