Metadata-Version: 2.1
Name: scapy-nflog-capture3
Version: 22.11.3
Summary: Driver for scapy to allow capturing packets via Linux NFLOG interface (Python 3)
Home-page: http://github.com/thekix/scapy-nflog-capture
Author: Rodolfo García Peñas (kix)
Author-email: kix@kix.es
License: WTFPL
Keywords: nflog,scapy,plugin,driver,traffic,analysis,analyze,capture,dump,network,linux,security,sniffer,spoof,netfilter,iptables,xtables,filter,filtering,firewall,audit,cffi,libnetfilter_log,socket
Classifier: Development Status :: 4 - Beta
Classifier: Intended Audience :: Developers
Classifier: Intended Audience :: System Administrators
Classifier: Intended Audience :: Telecommunications Industry
Classifier: License :: OSI Approved
Classifier: Operating System :: POSIX :: Linux
Classifier: Programming Language :: Python
Classifier: Programming Language :: Python :: 3
Classifier: Programming Language :: Python :: 3 :: Only
Classifier: Topic :: Security
Classifier: Topic :: System :: Networking :: Monitoring
Classifier: Topic :: System :: Operating System Kernels :: Linux
License-File: COPYING
